multiagent_framework/Agent.py
multiagent_framework/DefaultTools/RetriveInfoRAG.py
multiagent_framework/DefaultTools/SaveInfoRAG.py
multiagent_framework/JSONManager.py
multiagent_framework/LLMConfig.py
multiagent_framework/LLMManager.py
multiagent_framework/MultiAgentFramework.py
multiagent_framework/__init__.py
multiagent_framework/multiagent_cli.py
multiagent_framework/rag_system.py
multiagent_framework/templates/agent.yaml
multiagent_framework/templates/example.txt
multiagent_framework/templates/project/config.yaml
multiagent_framework/templates/project/custom_rag.py
multiagent_framework/templates/tool.py
multiagent_framework-0.0.6.dist-info/METADATA
multiagent_framework-0.0.6.dist-info/WHEEL
multiagent_framework-0.0.6.dist-info/RECORD
