Metadata-Version: 2.1
Name: multiagent-framework
Version: 0.0.6
Summary: MultiAgent Framework is a powerful Python-based system for creating and managing multi-agent conversations and workflows. It supports multiple Language Model providers, custom tool integration, and includes a Retrieval-Augmented Generation (RAG) system. The framework enables seamless interaction between AI agents, making it ideal for complex task automation, interactive AI assistants, and decision support systems.
License: MIT
Author: Gowrav Vishwakarma
Author-email: gowravvishwkarma@gmail.com
Requires-Python: >=3.12,<4.0
Classifier: License :: OSI Approved :: MIT License
Classifier: Programming Language :: Python :: 3
Classifier: Programming Language :: Python :: 3.12
Requires-Dist: beautifulsoup4 (==4.12.3)
Requires-Dist: chromadb (==0.5.4)
Requires-Dist: colorama (==0.4.6)
Requires-Dist: googlesearch-python (==1.2.4)
Requires-Dist: html2text (==2024.2.26)
Requires-Dist: numpy (==1.26.4)
Requires-Dist: ollama (==0.2.1)
Requires-Dist: onnxruntime (==1.18.1)
Requires-Dist: openai (==1.35.10)
Requires-Dist: protobuf (>=3.20.0,<4.0.0)
Requires-Dist: pydantic (==2.8.2)
Requires-Dist: python-dotenv (==1.0.1)
Requires-Dist: pyyaml (==6.0.1)
Requires-Dist: requests (==2.32.3)
Requires-Dist: setuptools (==70.3.0)
Requires-Dist: tiktoken (>=0.7.0,<0.8.0)
Requires-Dist: uvicorn (==0.30.1)
